ImageLabelingTool/Image_Labeling.py
ImageLabelingTool/__init__.py
ImageLabelingTool-0.1.dist-info/LICENSE
ImageLabelingTool-0.1.dist-info/METADATA
ImageLabelingTool-0.1.dist-info/WHEEL
ImageLabelingTool-0.1.dist-info/top_level.txt
ImageLabelingTool-0.1.dist-info/RECORD
