Metadata-Version: 2.1
Name: ImageLabelingTool
Version: 0.1
Summary: Simplify the process of labeling images or video frames with bounding boxes for object detection tasks.
Home-page: https://github.com/Rathoreatri03/Model_Trainer
Author: Atri Rathore
Author-email: <rathoreatri@gmail.com>
Keywords: python,image labeling,object detection,bounding box annotation
Classifier: Development Status :: 1 - Planning
Classifier: Intended Audience :: Developers
Classifier: Programming Language :: Python :: 3
Classifier: Operating System :: Unix
Classifier: Operating System :: MacOS :: MacOS X
Classifier: Operating System :: Microsoft :: Windows
License-File: LICENSE
Requires-Dist: opencv-python
Requires-Dist: keyboard
